MicroCast/__init__.py
MicroCast/account.cp37-win32.pyd
MicroCast/base.cp37-win32.pyd
MicroCast/channel.cp37-win32.pyd
MicroCast/haohanCtoCsAPI.dll
MicroCast-0.2.2.dist-info/METADATA
MicroCast-0.2.2.dist-info/WHEEL
MicroCast-0.2.2.dist-info/top_level.txt
MicroCast-0.2.2.dist-info/RECORD
